mkdocs_git_show_history_log_plugin/__init__.py
mkdocs_git_show_history_log_plugin/gitinfo.py
mkdocs_git_show_history_log_plugin/plugin.py
mkdocs_git_show_history_log_plugin-0.2.dist-info/DESCRIPTION.rst
mkdocs_git_show_history_log_plugin-0.2.dist-info/METADATA
mkdocs_git_show_history_log_plugin-0.2.dist-info/RECORD
mkdocs_git_show_history_log_plugin-0.2.dist-info/WHEEL
mkdocs_git_show_history_log_plugin-0.2.dist-info/entry_points.txt
mkdocs_git_show_history_log_plugin-0.2.dist-info/metadata.json
mkdocs_git_show_history_log_plugin-0.2.dist-info/top_level.txt
