Metadata-Version: 2.0
Name: mkdocs-git-show-history-log-plugin
Version: 0.2
Summary: MkDocs plugin for showing a history log for a specified markdown file
Home-page: https://github.com/pawelsikora/mkdocs-git-show-history-log-plugin/
Author: Pawel Sikora
Author-email: sikor6@gmail.com
License: MIT
Keywords: mkdocs git meta yaml frontmatter
Platform: UNKNOWN
Requires-Python: >=3.6
Requires-Dist: mkdocs (>=1.1)
Requires-Dist: GitPython
Requires-Dist: jinja2
